git_upm_publisher/__init__.py
git_upm_publisher/config_maker.py
git_upm_publisher/main.py
git_upm_publisher/package_json_creator.py
git_upm_publisher/package_json_updater.py
git_upm_publisher/upm_publisher.py
git_upm_publisher/utils/__init__.py
git_upm_publisher/utils/config_reader.py
git_upm_publisher/utils/discover.py
git_upm_publisher/utils/git_manager.py
git_upm_publisher/utils/package_json_obj.py
git_upm_publisher/utils/package_manager.py
git_upm_publisher-0.0.5.dist-info/LICENSE
git_upm_publisher-0.0.5.dist-info/METADATA
git_upm_publisher-0.0.5.dist-info/WHEEL
git_upm_publisher-0.0.5.dist-info/entry_points.txt
git_upm_publisher-0.0.5.dist-info/top_level.txt
git_upm_publisher-0.0.5.dist-info/RECORD
