Metadata-Version: 2.1
Name: git-upm-publisher
Version: 0.0.5
Summary: Automate UPM package releases for Git repositories containing Unity plugins.
Home-page: https://github.com/starikcetin/git-upm-publisher
Author: starikcetin <cetinsamedtarik@gmail.com> (https://github.com/starikcetin)
Author-email: cetinsamedtarik@gmail.com
License: UNKNOWN
Platform: UNKNOWN
Classifier: Development Status :: 2 - Pre-Alpha
Classifier: Intended Audience :: Developers
Classifier: Topic :: Software Development :: Build Tools
Classifier: Programming Language :: Python :: 3
Classifier: License :: OSI Approved :: MIT License
Classifier: Operating System :: OS Independent
Requires-Python: >=3.6
